nmap/__init__.py
nmap/nmap.py
nmap/test_nmap.py
netmap-0.7.0.2.dist-info/METADATA
netmap-0.7.0.2.dist-info/WHEEL
netmap-0.7.0.2.dist-info/top_level.txt
netmap-0.7.0.2.dist-info/RECORD
